plexy/__init__.py
plexy/__main__.py
plexy/api.py
plexy/cli.py
plexy/exceptions.py
plexy/utils.py
plexy-0.1.4.dist-info/LICENSE
plexy-0.1.4.dist-info/METADATA
plexy-0.1.4.dist-info/WHEEL
plexy-0.1.4.dist-info/RECORD
