Metadata-Version: 2.1
Name: plexy
Version: 0.1.4
Summary: Your Plex, your way
Home-page: https://github.com/ratoaq2/plexy
License: MIT
Keywords: video,plex,audio,subtitles,preferences,dubbed,subbed,original,language,foreign,movie,episode,tv,track,shows,series
Author: Rato
Requires-Python: >=3.9.0,<4.0.0
Classifier: Development Status :: 5 - Production/Stable
Classifier: Intended Audience :: Developers
Classifier: License :: OSI Approved :: Apache Software License
Classifier: License :: OSI Approved :: MIT License
Classifier: Operating System :: OS Independent
Classifier: Programming Language :: Python
Classifier: Programming Language :: Python :: 3
Classifier: Programming Language :: Python :: 3.9
Classifier: Programming Language :: Python :: 3.10
Classifier: Programming Language :: Python :: 3.11
Classifier: Programming Language :: Python :: 3.12
Classifier: Programming Language :: Python :: 3 :: Only
Classifier: Topic :: Multimedia :: Video
Classifier: Topic :: Software Development :: Libraries :: Python Modules
Requires-Dist: PlexAPI (>=4.12.1,<5.0.0)
Requires-Dist: appdirs (>=1.4.4,<2.0.0)
Requires-Dist: babelfish (>=0.6.0,<0.7.0)
Requires-Dist: click (>=8.1.3,<9.0.0)
Requires-Dist: pyyaml (>=6.0,<7.0)
Requires-Dist: trakit (>=0.2.2,<0.3.0)
Project-URL: Repository, https://github.com/ratoaq2/plexy
